PIPBUILDER/__init__.py
nova_py_pip_builder-0.4.dist-info/METADATA
nova_py_pip_builder-0.4.dist-info/WHEEL
nova_py_pip_builder-0.4.dist-info/top_level.txt
nova_py_pip_builder-0.4.dist-info/RECORD
