Metadata-Version: 2.1
Name: nova_py_pip_builder
Version: 0.4
Summary: Module pour exécuter un fichier .exe
Author: IMCSX BBY
Author-email: booking.biremont@gmail.com
